AuthenticationModels/__init__.py
AuthenticationModels/models.py
AuthenticationModels/schemas.py
model_authentication_nibata-0.2.1.dist-info/METADATA
model_authentication_nibata-0.2.1.dist-info/WHEEL
model_authentication_nibata-0.2.1.dist-info/top_level.txt
model_authentication_nibata-0.2.1.dist-info/RECORD
